enthusiast_agent_ocr_to_order/__init__.py
enthusiast_agent_ocr_to_order/agent.py
enthusiast_agent_ocr_to_order/config.py
enthusiast_agent_ocr_to_order/medusa_api_client.py
enthusiast_agent_ocr_to_order/prompt.py
enthusiast_agent_ocr_to_order/re_act/__init__.py
enthusiast_agent_ocr_to_order/re_act/agent.py
enthusiast_agent_ocr_to_order/re_act/config.py
enthusiast_agent_ocr_to_order/re_act/prompt.py
enthusiast_agent_ocr_to_order/tools/__init__.py
enthusiast_agent_ocr_to_order/tools/place_order_tool.py
enthusiast_agent_ocr_to_order-1.2.0.dist-info/METADATA
enthusiast_agent_ocr_to_order-1.2.0.dist-info/WHEEL
enthusiast_agent_ocr_to_order-1.2.0.dist-info/RECORD
