Metadata-Version: 2.4
Name: enthusiast-agent-ocr-to-order
Version: 1.2.0
Summary: Purchase Order OCR Agent for Enthusiast
Author: Damian Sowiński
Author-email: damian.sowinski@upsidelab.io
Requires-Python: >=3.10,<4
Classifier: Programming Language :: Python :: 3
Classifier: Programming Language :: Python :: 3.10
Classifier: Programming Language :: Python :: 3.11
Classifier: Programming Language :: Python :: 3.12
Classifier: Programming Language :: Python :: 3.13
Classifier: Programming Language :: Python :: 3.14
Requires-Dist: enthusiast-agent-product-search (>=1.2.0,<2.0.0)
Requires-Dist: enthusiast-common (>=1.5.0,<2.0.0)
Requires-Dist: enthusiast_agent_re_act (>=1.2.0)
Requires-Dist: enthusiast_agent_tool_calling (>=1.0.0)
Requires-Dist: langchain (>=0.3.26,<0.4.0)
Project-URL: Documentation, https://upsidelab.io/tools/enthusiast/agents/purchase-order-ocr
Project-URL: Homepage, https://upsidelab.io/tools/enthusiast
Project-URL: Issues, https://github.com/upsidelab/enthusiast/issues
Project-URL: Repository, https://github.com/upsidelab/enthusiast.git
